LICENSE
README.rst
setup.cfg
setup.py
docs/changelog.rst
src/senaite/__init__.py
src/senaite.abx.egg-info/PKG-INFO
src/senaite.abx.egg-info/SOURCES.txt
src/senaite.abx.egg-info/dependency_links.txt
src/senaite.abx.egg-info/entry_points.txt
src/senaite.abx.egg-info/namespace_packages.txt
src/senaite.abx.egg-info/not-zip-safe
src/senaite.abx.egg-info/requires.txt
src/senaite.abx.egg-info/top_level.txt
src/senaite/abx/__init__.py
src/senaite/abx/config.py
src/senaite/abx/configure.zcml
src/senaite/abx/interfaces.py
src/senaite/abx/setuphandlers.py
src/senaite/abx/browser/__init__.py
src/senaite/abx/browser/configure.zcml
src/senaite/abx/browser/content/__init__.py
src/senaite/abx/browser/content/antibioticclassfolder.py
src/senaite/abx/browser/content/antibioticfolder.py
src/senaite/abx/browser/content/configure.zcml
src/senaite/abx/browser/static/assets/icons/antibiotic.svg
src/senaite/abx/browser/static/assets/icons/antibiotic_class.svg
src/senaite/abx/browser/theme/__init__.py
src/senaite/abx/browser/theme/configure.zcml
src/senaite/abx/browser/theme/icons.py
src/senaite/abx/content/__init__.py
src/senaite/abx/content/antibiotic.py
src/senaite/abx/content/antibioticclass.py
src/senaite/abx/content/antibioticclassfolder.py
src/senaite/abx/content/antibioticfolder.py
src/senaite/abx/locales/senaite.abx.pot
src/senaite/abx/locales/cs/LC_MESSAGES/senaite.abx.po
src/senaite/abx/locales/de/LC_MESSAGES/senaite.abx.po
src/senaite/abx/locales/en/LC_MESSAGES/senaite.abx.po
src/senaite/abx/locales/es/LC_MESSAGES/senaite.abx.po
src/senaite/abx/profiles/default/browserlayer.xml
src/senaite/abx/profiles/default/metadata.xml
src/senaite/abx/profiles/default/senaite.abx.txt
src/senaite/abx/profiles/default/types.xml
src/senaite/abx/profiles/default/workflows.xml
src/senaite/abx/profiles/default/types/Antibiotic.xml
src/senaite/abx/profiles/default/types/AntibioticClass.xml
src/senaite/abx/profiles/default/types/AntibioticClassFolder.xml
src/senaite/abx/profiles/default/types/AntibioticFolder.xml
src/senaite/abx/profiles/uninstall/browserlayer.xml
src/senaite/abx/profiles/uninstall/senaite.abx.uninstall.txt
src/senaite/abx/upgrade/__init__.py
src/senaite/abx/upgrade/configure.zcml
src/senaite/abx/upgrade/v01_01_000.py
src/senaite/abx/upgrade/v01_02_000.py
src/senaite/abx/upgrade/v01_02_000.zcml
